xadix/__init__.py
xadix/argparse_tree/__init__.py
xadix/argparse_tree/_version.py
xadix/argparse_tree/argparse_tree.py
xadix/argparse_tree/argparse_tree_min.py
xadix.argparse_tree-0.2.0.dist-info/DESCRIPTION.rst
xadix.argparse_tree-0.2.0.dist-info/METADATA
xadix.argparse_tree-0.2.0.dist-info/RECORD
xadix.argparse_tree-0.2.0.dist-info/WHEEL
xadix.argparse_tree-0.2.0.dist-info/entry_points.txt
xadix.argparse_tree-0.2.0.dist-info/metadata.json
xadix.argparse_tree-0.2.0.dist-info/top_level.txt
