Metadata-Version: 2.0
Name: xadix.argparse-tree
Version: 0.2.0
Summary: This library makes it easier to work with many nested subcommands
Home-page: https://gitlab.com/xadix/argparse_tree
License: CC0-1.0
Platform: UNKNOWN
Classifier: Development Status :: 3 - Alpha
Classifier: Programming Language :: Python :: 3
Requires-Python: >=3, <4
Provides-Extra: dev
Provides-Extra: test
Provides-Extra: dev
Requires-Dist: check-manifest; extra == 'dev'
Provides-Extra: test
Requires-Dist: coverage; extra == 'test'
Requires-Dist: pytest; extra == 'test'
Requires-Dist: pytest-pylint; extra == 'test'
Requires-Dist: pylint; extra == 'test'
